fastapi_datatables/__init__.py
fastapi_datatables/filtration.py
fastapi_datatables/operations.py
fastapi_datatables/query.py
fastapi_datatables/schemas.py
fastapi_datatables/table.py
fastapi_datatables-0.6.2.dist-info/LICENSE
fastapi_datatables-0.6.2.dist-info/WHEEL
fastapi_datatables-0.6.2.dist-info/METADATA
fastapi_datatables-0.6.2.dist-info/RECORD
